{
    "$defs": {
        "aws_kendra_data_source": {
            "properties": {
                "arn": {
                    "type": "string"
                },
                "configuration": {
                    "properties": {
                        "s3_configuration": {
                            "properties": {
                                "access_control_list_configuration": {
                                    "properties": {
                                        "key_path": {
                                            "type": "string"
                                        }
                                    },
                                    "required": [

                                    ],
                                    "type": "object"
                                },
                                "bucket_name": {
                                    "type": "string"
                                },
                                "documents_metadata_configuration": {
                                    "properties": {
                                        "s3_prefix": {
                                            "type": "string"
                                        }
                                    },
                                    "required": [

                                    ],
                                    "type": "object"
                                },
                                "exclusion_patterns": {
                                    "items": {
                                        "type": "string"
                                    },
                                    "type": "array",
                                    "uniqueItems": true
                                },
                                "inclusion_patterns": {
                                    "items": {
                                        "type": "string"
                                    },
                                    "type": "array",
                                    "uniqueItems": true
                                },
                                "inclusion_prefixes": {
                                    "items": {
                                        "type": "string"
                                    },
                                    "type": "array",
                                    "uniqueItems": true
                                }
                            },
                            "required": [
                                "bucket_name"
                            ],
                            "type": "object"
                        },
                        "web_crawler_configuration": {
                            "properties": {
                                "authentication_configuration": {
                                    "properties": {
                                        "basic_authentication": {
                                            "items": {
                                                "properties": {
                                                    "credentials": {
                                                        "type": "string"
                                                    },
                                                    "host": {
                                                        "type": "string"
                                                    },
                                                    "port": {
                                                        "type": "number"
                                                    }
                                                },
                                                "required": [
                                                    "credentials",
                                                    "host",
                                                    "port"
                                                ],
                                                "type": "object"
                                            },
                                            "type": "array"
                                        }
                                    },
                                    "required": [

                                    ],
                                    "type": "object"
                                },
                                "crawl_depth": {
                                    "type": "number"
                                },
                                "max_content_size_per_page_in_mega_bytes": {
                                    "type": "number"
                                },
                                "max_links_per_page": {
                                    "type": "number"
                                },
                                "max_urls_per_minute_crawl_rate": {
                                    "type": "number"
                                },
                                "proxy_configuration": {
                                    "properties": {
                                        "credentials": {
                                            "type": "string"
                                        },
                                        "host": {
                                            "type": "string"
                                        },
                                        "port": {
                                            "type": "number"
                                        }
                                    },
                                    "required": [
                                        "host",
                                        "port"
                                    ],
                                    "type": "object"
                                },
                                "url_exclusion_patterns": {
                                    "items": {
                                        "type": "string"
                                    },
                                    "type": "array",
                                    "uniqueItems": true
                                },
                                "url_inclusion_patterns": {
                                    "items": {
                                        "type": "string"
                                    },
                                    "type": "array",
                                    "uniqueItems": true
                                },
                                "urls": {
                                    "properties": {
                                        "seed_url_configuration": {
                                            "properties": {
                                                "seed_urls": {
                                                    "items": {
                                                        "type": "string"
                                                    },
                                                    "type": "array",
                                                    "uniqueItems": true
                                                },
                                                "web_crawler_mode": {
                                                    "type": "string"
                                                }
                                            },
                                            "required": [
                                                "seed_urls"
                                            ],
                                            "type": "object"
                                        },
                                        "site_maps_configuration": {
                                            "properties": {
                                                "site_maps": {
                                                    "items": {
                                                        "type": "string"
                                                    },
                                                    "type": "array",
                                                    "uniqueItems": true
                                                }
                                            },
                                            "required": [
                                                "site_maps"
                                            ],
                                            "type": "object"
                                        }
                                    },
                                    "required": [

                                    ],
                                    "type": "object"
                                }
                            },
                            "required": [
                                "urls"
                            ],
                            "type": "object"
                        }
                    },
                    "required": [

                    ],
                    "type": "object"
                },
                "count": {
                    "type": "number"
                },
                "created_at": {
                    "type": "string"
                },
                "custom_document_enrichment_configuration": {
                    "properties": {
                        "inline_configurations": {
                            "items": {
                                "properties": {
                                    "condition": {
                                        "properties": {
                                            "condition_document_attribute_key": {
                                                "type": "string"
                                            },
                                            "condition_on_value": {
                                                "properties": {
                                                    "date_value": {
                                                        "type": "string"
                                                    },
                                                    "long_value": {
                                                        "type": "number"
                                                    },
                                                    "string_list_value": {
                                                        "items": {
                                                            "type": "string"
                                                        },
                                                        "type": "array",
                                                        "uniqueItems": true
                                                    },
                                                    "string_value": {
                                                        "type": "string"
                                                    }
                                                },
                                                "required": [

                                                ],
                                                "type": "object"
                                            },
                                            "operator": {
                                                "type": "string"
                                            }
                                        },
                                        "required": [
                                            "condition_document_attribute_key",
                                            "operator"
                                        ],
                                        "type": "object"
                                    },
                                    "document_content_deletion": {
                                        "type": "boolean"
                                    },
                                    "target": {
                                        "properties": {
                                            "target_document_attribute_key": {
                                                "type": "string"
                                            },
                                            "target_document_attribute_value": {
                                                "properties": {
                                                    "date_value": {
                                                        "type": "string"
                                                    },
                                                    "long_value": {
                                                        "type": "number"
                                                    },
                                                    "string_list_value": {
                                                        "items": {
                                                            "type": "string"
                                                        },
                                                        "type": "array",
                                                        "uniqueItems": true
                                                    },
                                                    "string_value": {
                                                        "type": "string"
                                                    }
                                                },
                                                "required": [

                                                ],
                                                "type": "object"
                                            },
                                            "target_document_attribute_value_deletion": {
                                                "type": "boolean"
                                            }
                                        },
                                        "required": [

                                        ],
                                        "type": "object"
                                    }
                                },
                                "required": [

                                ],
                                "type": "object"
                            },
                            "type": "array"
                        },
                        "post_extraction_hook_configuration": {
                            "properties": {
                                "invocation_condition": {
                                    "properties": {
                                        "condition_document_attribute_key": {
                                            "type": "string"
                                        },
                                        "condition_on_value": {
                                            "properties": {
                                                "date_value": {
                                                    "type": "string"
                                                },
                                                "long_value": {
                                                    "type": "number"
                                                },
                                                "string_list_value": {
                                                    "items": {
                                                        "type": "string"
                                                    },
                                                    "type": "array",
                                                    "uniqueItems": true
                                                },
                                                "string_value": {
                                                    "type": "string"
                                                }
                                            },
                                            "required": [

                                            ],
                                            "type": "object"
                                        },
                                        "operator": {
                                            "type": "string"
                                        }
                                    },
                                    "required": [
                                        "condition_document_attribute_key",
                                        "operator"
                                    ],
                                    "type": "object"
                                },
                                "lambda_arn": {
                                    "type": "string"
                                },
                                "s3_bucket": {
                                    "type": "string"
                                }
                            },
                            "required": [
                                "lambda_arn",
                                "s3_bucket"
                            ],
                            "type": "object"
                        },
                        "pre_extraction_hook_configuration": {
                            "properties": {
                                "invocation_condition": {
                                    "properties": {
                                        "condition_document_attribute_key": {
                                            "type": "string"
                                        },
                                        "condition_on_value": {
                                            "properties": {
                                                "date_value": {
                                                    "type": "string"
                                                },
                                                "long_value": {
                                                    "type": "number"
                                                },
                                                "string_list_value": {
                                                    "items": {
                                                        "type": "string"
                                                    },
                                                    "type": "array",
                                                    "uniqueItems": true
                                                },
                                                "string_value": {
                                                    "type": "string"
                                                }
                                            },
                                            "required": [

                                            ],
                                            "type": "object"
                                        },
                                        "operator": {
                                            "type": "string"
                                        }
                                    },
                                    "required": [
                                        "condition_document_attribute_key",
                                        "operator"
                                    ],
                                    "type": "object"
                                },
                                "lambda_arn": {
                                    "type": "string"
                                },
                                "s3_bucket": {
                                    "type": "string"
                                }
                            },
                            "required": [
                                "lambda_arn",
                                "s3_bucket"
                            ],
                            "type": "object"
                        },
                        "role_arn": {
                            "type": "string"
                        }
                    },
                    "required": [

                    ],
                    "type": "object"
                },
                "data_source_id": {
                    "type": "string"
                },
                "depends_on": {
                    "items": {
                        "type": "string"
                    },
                    "type": "array"
                },
                "description": {
                    "type": "string"
                },
                "error_message": {
                    "type": "string"
                },
                "id": {
                    "type": "string"
                },
                "index_id": {
                    "type": "string"
                },
                "language_code": {
                    "type": "string"
                },
                "lifecycle": {
                    "properties": {
                        "create_before_destroy": {
                            "type": "boolean"
                        },
                        "ignore_changes": {
                            "items": {
                                "type": "string"
                            },
                            "type": "array"
                        },
                        "postcondition": {
                            "properties": {
                                "condition": {
                                    "type": "boolean"
                                },
                                "error_message": {
                                    "type": "string"
                                }
                            },
                            "type": "object"
                        },
                        "precondition": {
                            "properties": {
                                "condition": {
                                    "type": "boolean"
                                },
                                "error_message": {
                                    "type": "string"
                                }
                            },
                            "type": "object"
                        },
                        "prevent_destroy": {
                            "type": "boolean"
                        },
                        "replace_triggered_by": {
                            "items": {
                                "type": "string"
                            },
                            "type": "array"
                        }
                    },
                    "type": "object"
                },
                "name": {
                    "type": "string"
                },
                "provider": {
                    "type": "string"
                },
                "provisioner": {
                    "items": {
                        "type": "object"
                    },
                    "type": "array"
                },
                "role_arn": {
                    "type": "string"
                },
                "schedule": {
                    "type": "string"
                },
                "status": {
                    "type": "string"
                },
                "tags": {
                    "additionalProperties": {
                        "type": "string"
                    },
                    "type": "object"
                },
                "tags_all": {
                    "additionalProperties": {
                        "type": "string"
                    },
                    "type": "object"
                },
                "timeouts": {
                    "properties": {
                        "create": {
                            "type": "string"
                        },
                        "delete": {
                            "type": "string"
                        },
                        "update": {
                            "type": "string"
                        }
                    },
                    "required": [

                    ],
                    "type": "object"
                },
                "type": {
                    "type": "string"
                },
                "updated_at": {
                    "type": "string"
                }
            },
            "required": [
                "index_id",
                "name",
                "type"
            ],
            "type": "object"
        },
        "aws_kendra_experience": {
            "properties": {
                "arn": {
                    "type": "string"
                },
                "configuration": {
                    "properties": {
                        "content_source_configuration": {
                            "properties": {
                                "data_source_ids": {
                                    "items": {
                                        "type": "string"
                                    },
                                    "type": "array",
                                    "uniqueItems": true
                                },
                                "direct_put_content": {
                                    "type": "boolean"
                                },
                                "faq_ids": {
                                    "items": {
                                        "type": "string"
                                    },
                                    "type": "array",
                                    "uniqueItems": true
                                }
                            },
                            "required": [

                            ],
                            "type": "object"
                        },
                        "user_identity_configuration": {
                            "properties": {
                                "identity_attribute_name": {
                                    "type": "string"
                                }
                            },
                            "required": [
                                "identity_attribute_name"
                            ],
                            "type": "object"
                        }
                    },
                    "required": [

                    ],
                    "type": "object"
                },
                "count": {
                    "type": "number"
                },
                "depends_on": {
                    "items": {
                        "type": "string"
                    },
                    "type": "array"
                },
                "description": {
                    "type": "string"
                },
                "endpoints": {
                    "items": {
                        "properties": {
                            "endpoint": {
                                "type": "string"
                            },
                            "endpoint_type": {
                                "type": "string"
                            }
                        },
                        "type": "object"
                    },
                    "type": "array",
                    "uniqueItems": true
                },
                "experience_id": {
                    "type": "string"
                },
                "id": {
                    "type": "string"
                },
                "index_id": {
                    "type": "string"
                },
                "lifecycle": {
                    "properties": {
                        "create_before_destroy": {
                            "type": "boolean"
                        },
                        "ignore_changes": {
                            "items": {
                                "type": "string"
                            },
                            "type": "array"
                        },
                        "postcondition": {
                            "properties": {
                                "condition": {
                                    "type": "boolean"
                                },
                                "error_message": {
                                    "type": "string"
                                }
                            },
                            "type": "object"
                        },
                        "precondition": {
                            "properties": {
                                "condition": {
                                    "type": "boolean"
                                },
                                "error_message": {
                                    "type": "string"
                                }
                            },
                            "type": "object"
                        },
                        "prevent_destroy": {
                            "type": "boolean"
                        },
                        "replace_triggered_by": {
                            "items": {
                                "type": "string"
                            },
                            "type": "array"
                        }
                    },
                    "type": "object"
                },
                "name": {
                    "type": "string"
                },
                "provider": {
                    "type": "string"
                },
                "provisioner": {
                    "items": {
                        "type": "object"
                    },
                    "type": "array"
                },
                "role_arn": {
                    "type": "string"
                },
                "status": {
                    "type": "string"
                },
                "timeouts": {
                    "properties": {
                        "create": {
                            "type": "string"
                        },
                        "delete": {
                            "type": "string"
                        },
                        "update": {
                            "type": "string"
                        }
                    },
                    "required": [

                    ],
                    "type": "object"
                }
            },
            "required": [
                "index_id",
                "name",
                "role_arn"
            ],
            "type": "object"
        },
        "aws_kendra_faq": {
            "properties": {
                "arn": {
                    "type": "string"
                },
                "count": {
                    "type": "number"
                },
                "created_at": {
                    "type": "string"
                },
                "depends_on": {
                    "items": {
                        "type": "string"
                    },
                    "type": "array"
                },
                "description": {
                    "type": "string"
                },
                "error_message": {
                    "type": "string"
                },
                "faq_id": {
                    "type": "string"
                },
                "file_format": {
                    "type": "string"
                },
                "id": {
                    "type": "string"
                },
                "index_id": {
                    "type": "string"
                },
                "language_code": {
                    "type": "string"
                },
                "lifecycle": {
                    "properties": {
                        "create_before_destroy": {
                            "type": "boolean"
                        },
                        "ignore_changes": {
                            "items": {
                                "type": "string"
                            },
                            "type": "array"
                        },
                        "postcondition": {
                            "properties": {
                                "condition": {
                                    "type": "boolean"
                                },
                                "error_message": {
                                    "type": "string"
                                }
                            },
                            "type": "object"
                        },
                        "precondition": {
                            "properties": {
                                "condition": {
                                    "type": "boolean"
                                },
                                "error_message": {
                                    "type": "string"
                                }
                            },
                            "type": "object"
                        },
                        "prevent_destroy": {
                            "type": "boolean"
                        },
                        "replace_triggered_by": {
                            "items": {
                                "type": "string"
                            },
                            "type": "array"
                        }
                    },
                    "type": "object"
                },
                "name": {
                    "type": "string"
                },
                "provider": {
                    "type": "string"
                },
                "provisioner": {
                    "items": {
                        "type": "object"
                    },
                    "type": "array"
                },
                "role_arn": {
                    "type": "string"
                },
                "s3_path": {
                    "properties": {
                        "bucket": {
                            "type": "string"
                        },
                        "key": {
                            "type": "string"
                        }
                    },
                    "required": [
                        "bucket",
                        "key"
                    ],
                    "type": "object"
                },
                "status": {
                    "type": "string"
                },
                "tags": {
                    "additionalProperties": {
                        "type": "string"
                    },
                    "type": "object"
                },
                "tags_all": {
                    "additionalProperties": {
                        "type": "string"
                    },
                    "type": "object"
                },
                "timeouts": {
                    "properties": {
                        "create": {
                            "type": "string"
                        },
                        "delete": {
                            "type": "string"
                        }
                    },
                    "required": [

                    ],
                    "type": "object"
                },
                "updated_at": {
                    "type": "string"
                }
            },
            "required": [
                "index_id",
                "name",
                "role_arn",
                "s3_path"
            ],
            "type": "object"
        },
        "aws_kendra_index": {
            "properties": {
                "arn": {
                    "type": "string"
                },
                "capacity_units": {
                    "properties": {
                        "query_capacity_units": {
                            "type": "number"
                        },
                        "storage_capacity_units": {
                            "type": "number"
                        }
                    },
                    "required": [

                    ],
                    "type": "object"
                },
                "count": {
                    "type": "number"
                },
                "created_at": {
                    "type": "string"
                },
                "depends_on": {
                    "items": {
                        "type": "string"
                    },
                    "type": "array"
                },
                "description": {
                    "type": "string"
                },
                "document_metadata_configuration_updates": {
                    "items": {
                        "properties": {
                            "name": {
                                "type": "string"
                            },
                            "relevance": {
                                "properties": {
                                    "duration": {
                                        "type": "string"
                                    },
                                    "freshness": {
                                        "type": "boolean"
                                    },
                                    "importance": {
                                        "type": "number"
                                    },
                                    "rank_order": {
                                        "type": "string"
                                    },
                                    "values_importance_map": {
                                        "additionalProperties": {
                                            "type": "number"
                                        },
                                        "type": "object"
                                    }
                                },
                                "required": [

                                ],
                                "type": "object"
                            },
                            "search": {
                                "properties": {
                                    "displayable": {
                                        "type": "boolean"
                                    },
                                    "facetable": {
                                        "type": "boolean"
                                    },
                                    "searchable": {
                                        "type": "boolean"
                                    },
                                    "sortable": {
                                        "type": "boolean"
                                    }
                                },
                                "required": [

                                ],
                                "type": "object"
                            },
                            "type": {
                                "type": "string"
                            }
                        },
                        "required": [
                            "name",
                            "type"
                        ],
                        "type": "object"
                    },
                    "type": "array"
                },
                "edition": {
                    "type": "string"
                },
                "error_message": {
                    "type": "string"
                },
                "id": {
                    "type": "string"
                },
                "index_statistics": {
                    "items": {
                        "properties": {
                            "faq_statistics": {
                                "items": {
                                    "properties": {
                                        "indexed_question_answers_count": {
                                            "type": "number"
                                        }
                                    },
                                    "type": "object"
                                },
                                "type": "array"
                            },
                            "text_document_statistics": {
                                "items": {
                                    "properties": {
                                        "indexed_text_bytes": {
                                            "type": "number"
                                        },
                                        "indexed_text_documents_count": {
                                            "type": "number"
                                        }
                                    },
                                    "type": "object"
                                },
                                "type": "array"
                            }
                        },
                        "type": "object"
                    },
                    "type": "array"
                },
                "lifecycle": {
                    "properties": {
                        "create_before_destroy": {
                            "type": "boolean"
                        },
                        "ignore_changes": {
                            "items": {
                                "type": "string"
                            },
                            "type": "array"
                        },
                        "postcondition": {
                            "properties": {
                                "condition": {
                                    "type": "boolean"
                                },
                                "error_message": {
                                    "type": "string"
                                }
                            },
                            "type": "object"
                        },
                        "precondition": {
                            "properties": {
                                "condition": {
                                    "type": "boolean"
                                },
                                "error_message": {
                                    "type": "string"
                                }
                            },
                            "type": "object"
                        },
                        "prevent_destroy": {
                            "type": "boolean"
                        },
                        "replace_triggered_by": {
                            "items": {
                                "type": "string"
                            },
                            "type": "array"
                        }
                    },
                    "type": "object"
                },
                "name": {
                    "type": "string"
                },
                "provider": {
                    "type": "string"
                },
                "provisioner": {
                    "items": {
                        "type": "object"
                    },
                    "type": "array"
                },
                "role_arn": {
                    "type": "string"
                },
                "server_side_encryption_configuration": {
                    "properties": {
                        "kms_key_id": {
                            "type": "string"
                        }
                    },
                    "required": [

                    ],
                    "type": "object"
                },
                "status": {
                    "type": "string"
                },
                "tags": {
                    "additionalProperties": {
                        "type": "string"
                    },
                    "type": "object"
                },
                "tags_all": {
                    "additionalProperties": {
                        "type": "string"
                    },
                    "type": "object"
                },
                "timeouts": {
                    "properties": {
                        "create": {
                            "type": "string"
                        },
                        "delete": {
                            "type": "string"
                        },
                        "update": {
                            "type": "string"
                        }
                    },
                    "required": [

                    ],
                    "type": "object"
                },
                "updated_at": {
                    "type": "string"
                },
                "user_context_policy": {
                    "type": "string"
                },
                "user_group_resolution_configuration": {
                    "properties": {
                        "user_group_resolution_mode": {
                            "type": "string"
                        }
                    },
                    "required": [
                        "user_group_resolution_mode"
                    ],
                    "type": "object"
                },
                "user_token_configurations": {
                    "properties": {
                        "json_token_type_configuration": {
                            "properties": {
                                "group_attribute_field": {
                                    "type": "string"
                                },
                                "user_name_attribute_field": {
                                    "type": "string"
                                }
                            },
                            "required": [
                                "group_attribute_field",
                                "user_name_attribute_field"
                            ],
                            "type": "object"
                        },
                        "jwt_token_type_configuration": {
                            "properties": {
                                "claim_regex": {
                                    "type": "string"
                                },
                                "group_attribute_field": {
                                    "type": "string"
                                },
                                "issuer": {
                                    "type": "string"
                                },
                                "key_location": {
                                    "type": "string"
                                },
                                "secrets_manager_arn": {
                                    "type": "string"
                                },
                                "url": {
                                    "type": "string"
                                },
                                "user_name_attribute_field": {
                                    "type": "string"
                                }
                            },
                            "required": [
                                "key_location"
                            ],
                            "type": "object"
                        }
                    },
                    "required": [

                    ],
                    "type": "object"
                }
            },
            "required": [
                "name",
                "role_arn"
            ],
            "type": "object"
        },
        "aws_kendra_query_suggestions_block_list": {
            "properties": {
                "arn": {
                    "type": "string"
                },
                "count": {
                    "type": "number"
                },
                "depends_on": {
                    "items": {
                        "type": "string"
                    },
                    "type": "array"
                },
                "description": {
                    "type": "string"
                },
                "id": {
                    "type": "string"
                },
                "index_id": {
                    "type": "string"
                },
                "lifecycle": {
                    "properties": {
                        "create_before_destroy": {
                            "type": "boolean"
                        },
                        "ignore_changes": {
                            "items": {
                                "type": "string"
                            },
                            "type": "array"
                        },
                        "postcondition": {
                            "properties": {
                                "condition": {
                                    "type": "boolean"
                                },
                                "error_message": {
                                    "type": "string"
                                }
                            },
                            "type": "object"
                        },
                        "precondition": {
                            "properties": {
                                "condition": {
                                    "type": "boolean"
                                },
                                "error_message": {
                                    "type": "string"
                                }
                            },
                            "type": "object"
                        },
                        "prevent_destroy": {
                            "type": "boolean"
                        },
                        "replace_triggered_by": {
                            "items": {
                                "type": "string"
                            },
                            "type": "array"
                        }
                    },
                    "type": "object"
                },
                "name": {
                    "type": "string"
                },
                "provider": {
                    "type": "string"
                },
                "provisioner": {
                    "items": {
                        "type": "object"
                    },
                    "type": "array"
                },
                "query_suggestions_block_list_id": {
                    "type": "string"
                },
                "role_arn": {
                    "type": "string"
                },
                "source_s3_path": {
                    "properties": {
                        "bucket": {
                            "type": "string"
                        },
                        "key": {
                            "type": "string"
                        }
                    },
                    "required": [
                        "bucket",
                        "key"
                    ],
                    "type": "object"
                },
                "status": {
                    "type": "string"
                },
                "tags": {
                    "additionalProperties": {
                        "type": "string"
                    },
                    "type": "object"
                },
                "tags_all": {
                    "additionalProperties": {
                        "type": "string"
                    },
                    "type": "object"
                },
                "timeouts": {
                    "properties": {
                        "create": {
                            "type": "string"
                        },
                        "delete": {
                            "type": "string"
                        },
                        "update": {
                            "type": "string"
                        }
                    },
                    "required": [

                    ],
                    "type": "object"
                }
            },
            "required": [
                "index_id",
                "name",
                "role_arn",
                "source_s3_path"
            ],
            "type": "object"
        },
        "aws_kendra_thesaurus": {
            "properties": {
                "arn": {
                    "type": "string"
                },
                "count": {
                    "type": "number"
                },
                "depends_on": {
                    "items": {
                        "type": "string"
                    },
                    "type": "array"
                },
                "description": {
                    "type": "string"
                },
                "id": {
                    "type": "string"
                },
                "index_id": {
                    "type": "string"
                },
                "lifecycle": {
                    "properties": {
                        "create_before_destroy": {
                            "type": "boolean"
                        },
                        "ignore_changes": {
                            "items": {
                                "type": "string"
                            },
                            "type": "array"
                        },
                        "postcondition": {
                            "properties": {
                                "condition": {
                                    "type": "boolean"
                                },
                                "error_message": {
                                    "type": "string"
                                }
                            },
                            "type": "object"
                        },
                        "precondition": {
                            "properties": {
                                "condition": {
                                    "type": "boolean"
                                },
                                "error_message": {
                                    "type": "string"
                                }
                            },
                            "type": "object"
                        },
                        "prevent_destroy": {
                            "type": "boolean"
                        },
                        "replace_triggered_by": {
                            "items": {
                                "type": "string"
                            },
                            "type": "array"
                        }
                    },
                    "type": "object"
                },
                "name": {
                    "type": "string"
                },
                "provider": {
                    "type": "string"
                },
                "provisioner": {
                    "items": {
                        "type": "object"
                    },
                    "type": "array"
                },
                "role_arn": {
                    "type": "string"
                },
                "source_s3_path": {
                    "properties": {
                        "bucket": {
                            "type": "string"
                        },
                        "key": {
                            "type": "string"
                        }
                    },
                    "required": [
                        "bucket",
                        "key"
                    ],
                    "type": "object"
                },
                "status": {
                    "type": "string"
                },
                "tags": {
                    "additionalProperties": {
                        "type": "string"
                    },
                    "type": "object"
                },
                "tags_all": {
                    "additionalProperties": {
                        "type": "string"
                    },
                    "type": "object"
                },
                "thesaurus_id": {
                    "type": "string"
                },
                "timeouts": {
                    "properties": {
                        "create": {
                            "type": "string"
                        },
                        "delete": {
                            "type": "string"
                        },
                        "update": {
                            "type": "string"
                        }
                    },
                    "required": [

                    ],
                    "type": "object"
                }
            },
            "required": [
                "index_id",
                "name",
                "role_arn",
                "source_s3_path"
            ],
            "type": "object"
        }
    },
    "properties": {
        "resource": {
            "properties": {
                "aws_kendra_data_source": {
                    "additionalProperties": {
                        "$refs": "#/$defs/aws_kendra_data_source"
                    },
                    "minProperties": 1,
                    "type": "object"
                },
                "aws_kendra_experience": {
                    "additionalProperties": {
                        "$refs": "#/$defs/aws_kendra_experience"
                    },
                    "minProperties": 1,
                    "type": "object"
                },
                "aws_kendra_faq": {
                    "additionalProperties": {
                        "$refs": "#/$defs/aws_kendra_faq"
                    },
                    "minProperties": 1,
                    "type": "object"
                },
                "aws_kendra_index": {
                    "additionalProperties": {
                        "$refs": "#/$defs/aws_kendra_index"
                    },
                    "minProperties": 1,
                    "type": "object"
                },
                "aws_kendra_query_suggestions_block_list": {
                    "additionalProperties": {
                        "$refs": "#/$defs/aws_kendra_query_suggestions_block_list"
                    },
                    "minProperties": 1,
                    "type": "object"
                },
                "aws_kendra_thesaurus": {
                    "additionalProperties": {
                        "$refs": "#/$defs/aws_kendra_thesaurus"
                    },
                    "minProperties": 1,
                    "type": "object"
                }
            },
            "type": "object"
        }
    }
}